{"type":"FeatureCollection","features":[{"type":"Feature","properties":{"LAMPPOST_N":"114/1/114/1A"},"geometry":{"type":"Point","coordinates":[103.91424798645357,1.3790448653264025]}},{"type":"Feature","properties":{"LAMPPOST_N":"359F"},"geometry":{"type":"Point","coordinates":[103.91695552441767,1.38315069557983]}},{"type":"Feature","properties":{"LAMPPOST_N":"161F"},"geometry":{"type":"Point","coordinates":[103.91004556132316,1.3761323773394611]}},{"type":"Feature","properties":{"LAMPPOST_N":"163F"},"geometry":{"type":"Point","coordinates":[103.91025267710737,1.3756659249872092]}},{"type":"Feature","properties":{"LAMPPOST_N":"162F"},"geometry":{"type":"Point","coordinates":[103.91012711231264,1.3758843256106428]}},{"type":"Feature","properties":{"LAMPPOST_N":"160S4F"},"geometry":{"type":"Point","coordinates":[103.91003694947602,1.3752658766910852]}},{"type":"Feature","properties":{"LAMPPOST_N":"94"},"geometry":{"type":"Point","coordinates":[103.91013287774807,1.375736761774138]}},{"type":"Feature","properties":{"LAMPPOST_N":"79S7"},"geometry":{"type":"Point","coordinates":[103.90854684145918,1.3728327950978791]}},{"type":"Feature","properties":{"LAMPPOST_N":"160S12"},"geometry":{"type":"Point","coordinates":[103.90930874203488,1.3733743304972819]}},{"type":"Feature","properties":{"LAMPPOST_N":"160S13"},"geometry":{"type":"Point","coordinates":[103.90922461338309,1.3731658114504552]}},{"type":"Feature","properties":{"LAMPPOST_N":"76S2"},"geometry":{"type":"Point","coordinates":[103.90911384894189,1.3728941484897843]}},{"type":"Feature","properties":{"LAMPPOST_N":"160S11"},"geometry":{"type":"Point","coordinates":[103.90937705862011,1.373555144036871]}},{"type":"Feature","properties":{"LAMPPOST_N":"79S5"},"geometry":{"type":"Point","coordinates":[103.90867398017367,1.3731696289666628]}},{"type":"Feature","properties":{"LAMPPOST_N":"79S3"},"geometry":{"type":"Point","coordinates":[103.90884463031475,1.373615489385858]}},{"type":"Feature","properties":{"LAMPPOST_N":"79S4"},"geometry":{"type":"Point","coordinates":[103.9087494260652,1.3733620614090658]}},{"type":"Feature","properties":{"LAMPPOST_N":"77"},"geometry":{"type":"Point","coordinates":[103.90865618866961,1.3728879779484016]}},{"type":"Feature","properties":{"LAMPPOST_N":"75"},"geometry":{"type":"Point","coordinates":[103.90849674009628,1.372422311625975]}},{"type":"Feature","properties":{"LAMPPOST_N":"78"},"geometry":{"type":"Point","coordinates":[103.90910863914941,1.3731324643466283]}},{"type":"Feature","properties":{"LAMPPOST_N":"53S3"},"geometry":{"type":"Point","coordinates":[103.90712216866679,1.3684739212752708]}},{"type":"Feature","properties":{"LAMPPOST_N":"160S3F"},"geometry":{"type":"Point","coordinates":[103.91007788705332,1.3755073767179038]}},{"type":"Feature","properties":{"LAMPPOST_N":"160S2F"},"geometry":{"type":"Point","coordinates":[103.9100789716153,1.3757553293651459]}},{"type":"Feature","properties":{"LAMPPOST_N":"160S1F"},"geometry":{"type":"Point","coordinates":[103.9100488150483,1.3759622249687742]}},{"type":"Feature","properties":{"LAMPPOST_N":"53S5"},"geometry":{"type":"Point","coordinates":[103.90726222205967,1.3689502644462317]}},{"type":"Feature","properties":{"LAMPPOST_N":"53S4"},"geometry":{"type":"Point","coordinates":[103.90718824525226,1.3686822500196465]}},{"type":"Feature","properties":{"LAMPPOST_N":"79S10F"},"geometry":{"type":"Point","coordinates":[103.90836979940616,1.372368123717321]}},{"type":"Feature","properties":{"LAMPPOST_N":"96"},"geometry":{"type":"Point","coordinates":[103.91040227939453,1.3760672014795914]}},{"type":"Feature","properties":{"LAMPPOST_N":"98S3"},"geometry":{"type":"Point","coordinates":[103.91048077570828,1.3760374797125312]}},{"type":"Feature","properties":{"LAMPPOST_N":"79S8"},"geometry":{"type":"Point","coordinates":[103.90848236113813,1.3726739103376866]}},{"type":"Feature","properties":{"LAMPPOST_N":"79S9"},"geometry":{"type":"Point","coordinates":[103.90842900848446,1.3725227012534913]}},{"type":"Feature","properties":{"LAMPPOST_N":"53"},"geometry":{"type":"Point","coordinates":[103.90690169653733,1.3676818265417392]}},{"type":"Feature","properties":{"LAMPPOST_N":"53S1"},"geometry":{"type":"Point","coordinates":[103.90699062034552,1.3679563050464991]}},{"type":"Feature","properties":{"LAMPPOST_N":"51"},"geometry":{"type":"Point","coordinates":[103.90681379061762,1.3673471775266826]}},{"type":"Feature","properties":{"LAMPPOST_N":"47"},"geometry":{"type":"Point","coordinates":[103.90646956179421,1.3662934832374682]}},{"type":"Feature","properties":{"LAMPPOST_N":"49"},"geometry":{"type":"Point","coordinates":[103.90671448516508,1.3669916448813781]}},{"type":"Feature","properties":{"LAMPPOST_N":"45"},"geometry":{"type":"Point","coordinates":[103.90596726530225,1.3649137028317986]}},{"type":"Feature","properties":{"LAMPPOST_N":"45/1/45/1A"},"geometry":{"type":"Point","coordinates":[103.90617295993044,1.3653757619555131]}},{"type":"Feature","properties":{"LAMPPOST_N":"39"},"geometry":{"type":"Point","coordinates":[103.90525910212732,1.363539010108721]}},{"type":"Feature","properties":{"LAMPPOST_N":"41"},"geometry":{"type":"Point","coordinates":[103.90551240488054,1.3639905162283092]}},{"type":"Feature","properties":{"LAMPPOST_N":"37"},"geometry":{"type":"Point","coordinates":[103.9050313803907,1.3630854909979762]}},{"type":"Feature","properties":{"LAMPPOST_N":"98S1"},"geometry":{"type":"Point","coordinates":[103.91088748552558,1.3766083475725384]}},{"type":"Feature","properties":{"LAMPPOST_N":"100"},"geometry":{"type":"Point","coordinates":[103.91149506403364,1.3771506137477176]}},{"type":"Feature","properties":{"LAMPPOST_N":"98S2"},"geometry":{"type":"Point","coordinates":[103.9106730903625,1.3763326432437528]}},{"type":"Feature","properties":{"LAMPPOST_N":"98"},"geometry":{"type":"Point","coordinates":[103.91113223590837,1.3768708095105822]}},{"type":"Feature","properties":{"LAMPPOST_N":"15S1"},"geometry":{"type":"Point","coordinates":[103.90348255931944,1.3604243861013927]}},{"type":"Feature","properties":{"LAMPPOST_N":"53S2"},"geometry":{"type":"Point","coordinates":[103.90707637014371,1.3682523402599436]}},{"type":"Feature","properties":{"LAMPPOST_N":"238S6"},"geometry":{"type":"Point","coordinates":[103.91661706866601,1.3826320679158028]}},{"type":"Feature","properties":{"LAMPPOST_N":"238S7"},"geometry":{"type":"Point","coordinates":[103.91652221559225,1.38287494028602]}},{"type":"Feature","properties":{"LAMPPOST_N":"238S8"},"geometry":{"type":"Point","coordinates":[103.91638242714282,1.3830943649461893]}},{"type":"Feature","properties":{"LAMPPOST_N":"115"},"geometry":{"type":"Point","coordinates":[103.9054750633392,1.3629459475261083]}},{"type":"Feature","properties":{"LAMPPOST_N":"79S6"},"geometry":{"type":"Point","coordinates":[103.90859523450312,1.3730073549559596]}},{"type":"Feature","properties":{"LAMPPOST_N":"43"},"geometry":{"type":"Point","coordinates":[103.90574269077264,1.3644429346700484]}},{"type":"Feature","properties":{"LAMPPOST_N":"109S3"},"geometry":{"type":"Point","coordinates":[103.91435705770492,1.379886485689692]}},{"type":"Feature","properties":{"LAMPPOST_N":"106S10"},"geometry":{"type":"Point","coordinates":[103.90422935834798,1.3606887924022777]}},{"type":"Feature","properties":{"LAMPPOST_N":"15S2"},"geometry":{"type":"Point","coordinates":[103.90361374210562,1.3606958738529575]}},{"type":"Feature","properties":{"LAMPPOST_N":"3/10"},"geometry":{"type":"Point","coordinates":[103.90290357504969,1.3593375129778544]}},{"type":"Feature","properties":{"LAMPPOST_N":"3/11"},"geometry":{"type":"Point","coordinates":[103.902759232025,1.359105529649484]}},{"type":"Feature","properties":{"LAMPPOST_N":"3/12"},"geometry":{"type":"Point","coordinates":[103.90263119769837,1.3588814682917194]}},{"type":"Feature","properties":{"LAMPPOST_N":"3/13"},"geometry":{"type":"Point","coordinates":[103.90245162038708,1.3586030470036135]}},{"type":"Feature","properties":{"LAMPPOST_N":"22"},"geometry":{"type":"Point","coordinates":[103.90441220064774,1.3612456801791]}},{"type":"Feature","properties":{"LAMPPOST_N":"106S11"},"geometry":{"type":"Point","coordinates":[103.90404773030168,1.3604125901099895]}},{"type":"Feature","properties":{"LAMPPOST_N":"20"},"geometry":{"type":"Point","coordinates":[103.9040281021656,1.360525207684463]}},{"type":"Feature","properties":{"LAMPPOST_N":"47/1/47/1A"},"geometry":{"type":"Point","coordinates":[103.90639090813487,1.36603236043636]}},{"type":"Feature","properties":{"LAMPPOST_N":"45/1"},"geometry":{"type":"Point","coordinates":[103.90633506610851,1.3658149677688356]}},{"type":"Feature","properties":{"LAMPPOST_N":"48"},"geometry":{"type":"Point","coordinates":[103.90670541090638,1.3657927296707313]}},{"type":"Feature","properties":{"LAMPPOST_N":"46"},"geometry":{"type":"Point","coordinates":[103.90662618230523,1.3655621912100753]}},{"type":"Feature","properties":{"LAMPPOST_N":"44"},"geometry":{"type":"Point","coordinates":[103.90652583938656,1.3653252320859801]}},{"type":"Feature","properties":{"LAMPPOST_N":"42"},"geometry":{"type":"Point","coordinates":[103.90644104726228,1.365111928561851]}},{"type":"Feature","properties":{"LAMPPOST_N":"40"},"geometry":{"type":"Point","coordinates":[103.90633646412344,1.3648641538197352]}},{"type":"Feature","properties":{"LAMPPOST_N":"38"},"geometry":{"type":"Point","coordinates":[103.90622737769466,1.3646448038875114]}},{"type":"Feature","properties":{"LAMPPOST_N":"36"},"geometry":{"type":"Point","coordinates":[103.90614021176174,1.364454855700927]}},{"type":"Feature","properties":{"LAMPPOST_N":"34"},"geometry":{"type":"Point","coordinates":[103.90602479656472,1.3642368920022865]}},{"type":"Feature","properties":{"LAMPPOST_N":"32"},"geometry":{"type":"Point","coordinates":[103.90588691566515,1.3639935262870466]}},{"type":"Feature","properties":{"LAMPPOST_N":"30"},"geometry":{"type":"Point","coordinates":[103.90578625809346,1.3637715259238175]}},{"type":"Feature","properties":{"LAMPPOST_N":"28"},"geometry":{"type":"Point","coordinates":[103.90563681502941,1.3635234842911457]}},{"type":"Feature","properties":{"LAMPPOST_N":"26"},"geometry":{"type":"Point","coordinates":[103.90522960495733,1.3627477207564656]}},{"type":"Feature","properties":{"LAMPPOST_N":"24"},"geometry":{"type":"Point","coordinates":[103.90484113521725,1.3620356181827094]}},{"type":"Feature","properties":{"LAMPPOST_N":"U111"},"geometry":{"type":"Point","coordinates":[103.90502570616529,1.3629628443810993]}},{"type":"Feature","properties":{"LAMPPOST_N":"U113"},"geometry":{"type":"Point","coordinates":[103.90522170710805,1.3629850518812061]}},{"type":"Feature","properties":{"LAMPPOST_N":"116"},"geometry":{"type":"Point","coordinates":[103.90561268450173,1.3633655781466534]}},{"type":"Feature","properties":{"LAMPPOST_N":"19"},"geometry":{"type":"Point","coordinates":[103.90382125860219,1.3608448805404152]}},{"type":"Feature","properties":{"LAMPPOST_N":"17"},"geometry":{"type":"Point","coordinates":[103.90368674855895,1.3606042890044971]}},{"type":"Feature","properties":{"LAMPPOST_N":"15"},"geometry":{"type":"Point","coordinates":[103.90329977590916,1.360057270847238]}},{"type":"Feature","properties":{"LAMPPOST_N":"13"},"geometry":{"type":"Point","coordinates":[103.90318457048124,1.3597890494645122]}},{"type":"Feature","properties":{"LAMPPOST_N":"11"},"geometry":{"type":"Point","coordinates":[103.90303017190175,1.3595147587917285]}},{"type":"Feature","properties":{"LAMPPOST_N":"9"},"geometry":{"type":"Point","coordinates":[103.90285046323079,1.3591697039069515]}},{"type":"Feature","properties":{"LAMPPOST_N":"21"},"geometry":{"type":"Point","coordinates":[103.90393238503488,1.3610624980284587]}},{"type":"Feature","properties":{"LAMPPOST_N":"23"},"geometry":{"type":"Point","coordinates":[103.90405487869363,1.3613099260277461]}},{"type":"Feature","properties":{"LAMPPOST_N":"25"},"geometry":{"type":"Point","coordinates":[103.90419703953766,1.3615522940068594]}},{"type":"Feature","properties":{"LAMPPOST_N":"27"},"geometry":{"type":"Point","coordinates":[103.90433300482124,1.361797943759917]}},{"type":"Feature","properties":{"LAMPPOST_N":"29"},"geometry":{"type":"Point","coordinates":[103.90446925463065,1.3620691083537126]}},{"type":"Feature","properties":{"LAMPPOST_N":"31"},"geometry":{"type":"Point","coordinates":[103.90460230914793,1.362307950820919]}},{"type":"Feature","properties":{"LAMPPOST_N":"33"},"geometry":{"type":"Point","coordinates":[103.9047544829308,1.3625940375384764]}},{"type":"Feature","properties":{"LAMPPOST_N":"35"},"geometry":{"type":"Point","coordinates":[103.90486267431277,1.3627801445175132]}},{"type":"Feature","properties":{"LAMPPOST_N":"17/1/17/1A"},"geometry":{"type":"Point","coordinates":[103.90361874981278,1.3601296879967348]}},{"type":"Feature","properties":{"LAMPPOST_N":"18"},"geometry":{"type":"Point","coordinates":[103.90373057811664,1.3599203968688198]}},{"type":"Feature","properties":{"LAMPPOST_N":"16"},"geometry":{"type":"Point","coordinates":[103.90360586276387,1.3597067154999114]}},{"type":"Feature","properties":{"LAMPPOST_N":"15/1/15/1A"},"geometry":{"type":"Point","coordinates":[103.90344985179605,1.3598186221577497]}},{"type":"Feature","properties":{"LAMPPOST_N":"14"},"geometry":{"type":"Point","coordinates":[103.90349694476011,1.359512565015321]}},{"type":"Feature","properties":{"LAMPPOST_N":"12"},"geometry":{"type":"Point","coordinates":[103.90336810487865,1.3592820645101538]}},{"type":"Feature","properties":{"LAMPPOST_N":"10"},"geometry":{"type":"Point","coordinates":[103.90326268057277,1.3590920426397395]}},{"type":"Feature","properties":{"LAMPPOST_N":"8"},"geometry":{"type":"Point","coordinates":[103.90310734419064,1.3588218820385376]}},{"type":"Feature","properties":{"LAMPPOST_N":"13/1/13/1A"},"geometry":{"type":"Point","coordinates":[103.9032442061866,1.35945355533238]}},{"type":"Feature","properties":{"LAMPPOST_N":"354F"},"geometry":{"type":"Point","coordinates":[103.91683813217897,1.3828261690242134]}},{"type":"Feature","properties":{"LAMPPOST_N":"361F"},"geometry":{"type":"Point","coordinates":[103.91673518378738,1.3833785216870362]}},{"type":"Feature","properties":{"LAMPPOST_N":"U114"},"geometry":{"type":"Point","coordinates":[103.90541864886241,1.3632386042102522]}},{"type":"Feature","properties":{"LAMPPOST_N":"U112"},"geometry":{"type":"Point","coordinates":[103.90518624847908,1.3632037464692648]}},{"type":"Feature","properties":{"LAMPPOST_N":"356F"},"geometry":{"type":"Point","coordinates":[103.91661018103643,1.3830606422790515]}},{"type":"Feature","properties":{"LAMPPOST_N":"73"},"geometry":{"type":"Point","coordinates":[103.90835035688467,1.371957461917639]}},{"type":"Feature","properties":{"LAMPPOST_N":"79S2"},"geometry":{"type":"Point","coordinates":[103.9089040099441,1.373757559534191]}},{"type":"Feature","properties":{"LAMPPOST_N":"79S1"},"geometry":{"type":"Point","coordinates":[103.90897112987697,1.3739438100034145]}},{"type":"Feature","properties":{"LAMPPOST_N":"79"},"geometry":{"type":"Point","coordinates":[103.90902971273748,1.3741184775708895]}},{"type":"Feature","properties":{"LAMPPOST_N":"81"},"geometry":{"type":"Point","coordinates":[103.90919028638709,1.374583644396585]}},{"type":"Feature","properties":{"LAMPPOST_N":"83"},"geometry":{"type":"Point","coordinates":[103.90931459718375,1.374936242737117]}},{"type":"Feature","properties":{"LAMPPOST_N":"85"},"geometry":{"type":"Point","coordinates":[103.9094835543258,1.3752752267826447]}},{"type":"Feature","properties":{"LAMPPOST_N":"90"},"geometry":{"type":"Point","coordinates":[103.90978632293813,1.3750984320311597]}},{"type":"Feature","properties":{"LAMPPOST_N":"88"},"geometry":{"type":"Point","coordinates":[103.90963236348203,1.3747360789383642]}},{"type":"Feature","properties":{"LAMPPOST_N":"86"},"geometry":{"type":"Point","coordinates":[103.90949796345814,1.37437503562365]}},{"type":"Feature","properties":{"LAMPPOST_N":"87"},"geometry":{"type":"Point","coordinates":[103.90962392027548,1.3755405661300282]}},{"type":"Feature","properties":{"LAMPPOST_N":"89"},"geometry":{"type":"Point","coordinates":[103.90989179266504,1.376005823454786]}},{"type":"Feature","properties":{"LAMPPOST_N":"5"},"geometry":{"type":"Point","coordinates":[103.90249670848658,1.3584913030534387]}},{"type":"Feature","properties":{"LAMPPOST_N":"1"},"geometry":{"type":"Point","coordinates":[103.90217697564714,1.3578262148255764]}},{"type":"Feature","properties":{"LAMPPOST_N":"3"},"geometry":{"type":"Point","coordinates":[103.90233755625536,1.3581683553089607]}},{"type":"Feature","properties":{"LAMPPOST_N":"2"},"geometry":{"type":"Point","coordinates":[103.9025395193883,1.3577739167394864]}},{"type":"Feature","properties":{"LAMPPOST_N":"4"},"geometry":{"type":"Point","coordinates":[103.90274883976315,1.358178116925072]}},{"type":"Feature","properties":{"LAMPPOST_N":"6"},"geometry":{"type":"Point","coordinates":[103.90294752150804,1.358544396229939]}},{"type":"Feature","properties":{"LAMPPOST_N":"7"},"geometry":{"type":"Point","coordinates":[103.90266564112588,1.3588240789482726]}},{"type":"Feature","properties":{"LAMPPOST_N":"51/2/51/2A"},"geometry":{"type":"Point","coordinates":[103.90729241651978,1.3681134922590914]}},{"type":"Feature","properties":{"LAMPPOST_N":"51/1/51/1A"},"geometry":{"type":"Point","coordinates":[103.90720484060289,1.3678836566358732]}},{"type":"Feature","properties":{"LAMPPOST_N":"49/1/49/1A"},"geometry":{"type":"Point","coordinates":[103.90658483050905,1.3666755976078324]}},{"type":"Feature","properties":{"LAMPPOST_N":"50S1"},"geometry":{"type":"Point","coordinates":[103.90684377397243,1.3659112927742332]}},{"type":"Feature","properties":{"LAMPPOST_N":"50"},"geometry":{"type":"Point","coordinates":[103.90688564676198,1.3660972018225777]}},{"type":"Feature","properties":{"LAMPPOST_N":"52"},"geometry":{"type":"Point","coordinates":[103.90709268976563,1.366875618114762]}},{"type":"Feature","properties":{"LAMPPOST_N":"54"},"geometry":{"type":"Point","coordinates":[103.90736812402909,1.3677287172114951]}},{"type":"Feature","properties":{"LAMPPOST_N":"56"},"geometry":{"type":"Point","coordinates":[103.90755902091448,1.3683169670716662]}},{"type":"Feature","properties":{"LAMPPOST_N":"58"},"geometry":{"type":"Point","coordinates":[103.90775061658955,1.3688837576337791]}},{"type":"Feature","properties":{"LAMPPOST_N":"60"},"geometry":{"type":"Point","coordinates":[103.90789839107028,1.369360651916933]}},{"type":"Feature","properties":{"LAMPPOST_N":"62"},"geometry":{"type":"Point","coordinates":[103.90800800218275,1.3697096372043875]}},{"type":"Feature","properties":{"LAMPPOST_N":"64"},"geometry":{"type":"Point","coordinates":[103.9081234135948,1.370029749138775]}},{"type":"Feature","properties":{"LAMPPOST_N":"66"},"geometry":{"type":"Point","coordinates":[103.90822366478207,1.3703605174750515]}},{"type":"Feature","properties":{"LAMPPOST_N":"68"},"geometry":{"type":"Point","coordinates":[103.90833103678999,1.3706356217065196]}},{"type":"Feature","properties":{"LAMPPOST_N":"70"},"geometry":{"type":"Point","coordinates":[103.90842744911187,1.370932423054762]}},{"type":"Feature","properties":{"LAMPPOST_N":"72"},"geometry":{"type":"Point","coordinates":[103.90858187461583,1.3714051945427301]}},{"type":"Feature","properties":{"LAMPPOST_N":"74"},"geometry":{"type":"Point","coordinates":[103.90876145147767,1.371965103272677]}},{"type":"Feature","properties":{"LAMPPOST_N":"76"},"geometry":{"type":"Point","coordinates":[103.90889927638025,1.3723440923384196]}},{"type":"Feature","properties":{"LAMPPOST_N":"76S1"},"geometry":{"type":"Point","coordinates":[103.90900419060304,1.372585336362622]}},{"type":"Feature","properties":{"LAMPPOST_N":"80"},"geometry":{"type":"Point","coordinates":[103.90918761410208,1.3733832065023601]}},{"type":"Feature","properties":{"LAMPPOST_N":"82"},"geometry":{"type":"Point","coordinates":[103.90928612689765,1.3736495983237849]}},{"type":"Feature","properties":{"LAMPPOST_N":"84"},"geometry":{"type":"Point","coordinates":[103.9093842603248,1.373965701857859]}},{"type":"Feature","properties":{"LAMPPOST_N":"55"},"geometry":{"type":"Point","coordinates":[103.90725221269929,1.3685378503993673]}},{"type":"Feature","properties":{"LAMPPOST_N":"57"},"geometry":{"type":"Point","coordinates":[103.90733782308796,1.3688060700516849]}},{"type":"Feature","properties":{"LAMPPOST_N":"59"},"geometry":{"type":"Point","coordinates":[103.90741577719032,1.3690595452110859]}},{"type":"Feature","properties":{"LAMPPOST_N":"61"},"geometry":{"type":"Point","coordinates":[103.90757585850862,1.3695923307445412]}},{"type":"Feature","properties":{"LAMPPOST_N":"63"},"geometry":{"type":"Point","coordinates":[103.90769796203588,1.3699229602345022]}},{"type":"Feature","properties":{"LAMPPOST_N":"65"},"geometry":{"type":"Point","coordinates":[103.90784170185636,1.370349844755134]}},{"type":"Feature","properties":{"LAMPPOST_N":"67"},"geometry":{"type":"Point","coordinates":[103.90795103105063,1.3707029200358147]}},{"type":"Feature","properties":{"LAMPPOST_N":"69"},"geometry":{"type":"Point","coordinates":[103.9080636953838,1.371100961537552]}},{"type":"Feature","properties":{"LAMPPOST_N":"71"},"geometry":{"type":"Point","coordinates":[103.90823209441653,1.3715492036161179]}},{"type":"Feature","properties":{"LAMPPOST_N":"107"},"geometry":{"type":"Point","coordinates":[103.91324861009466,1.3786954880113529]}},{"type":"Feature","properties":{"LAMPPOST_N":"109"},"geometry":{"type":"Point","coordinates":[103.91357218165157,1.3789040418650023]}},{"type":"Feature","properties":{"LAMPPOST_N":"109S1"},"geometry":{"type":"Point","coordinates":[103.9139069150781,1.3791327320609872]}},{"type":"Feature","properties":{"LAMPPOST_N":"109S2"},"geometry":{"type":"Point","coordinates":[103.91412622740832,1.3792785196947128]}},{"type":"Feature","properties":{"LAMPPOST_N":"113"},"geometry":{"type":"Point","coordinates":[103.91460409220437,1.379454716013804]}},{"type":"Feature","properties":{"LAMPPOST_N":"111"},"geometry":{"type":"Point","coordinates":[103.91404740768782,1.3791150866365944]}},{"type":"Feature","properties":{"LAMPPOST_N":"112"},"geometry":{"type":"Point","coordinates":[103.91398454831695,1.378693952166131]}},{"type":"Feature","properties":{"LAMPPOST_N":"110"},"geometry":{"type":"Point","coordinates":[103.91369537502857,1.3785234773184867]}},{"type":"Feature","properties":{"LAMPPOST_N":"108"},"geometry":{"type":"Point","coordinates":[103.9132311780216,1.3782488101439148]}},{"type":"Feature","properties":{"LAMPPOST_N":"106"},"geometry":{"type":"Point","coordinates":[103.91281323881014,1.3779914447979822]}},{"type":"Feature","properties":{"LAMPPOST_N":"104"},"geometry":{"type":"Point","coordinates":[103.91233390677243,1.377715562795873]}},{"type":"Feature","properties":{"LAMPPOST_N":"102"},"geometry":{"type":"Point","coordinates":[103.91182828155074,1.3773835396596985]}},{"type":"Feature","properties":{"LAMPPOST_N":"92"},"geometry":{"type":"Point","coordinates":[103.90994580691896,1.3754308669936022]}},{"type":"Feature","properties":{"LAMPPOST_N":"77/2/77/2A"},"geometry":{"type":"Point","coordinates":[103.9089767327205,1.3732520216348718]}},{"type":"Feature","properties":{"LAMPPOST_N":"77/1/77/1A"},"geometry":{"type":"Point","coordinates":[103.9088713273562,1.3729784997753605]}},{"type":"Feature","properties":{"LAMPPOST_N":"75/1/75/1A"},"geometry":{"type":"Point","coordinates":[103.9087964114056,1.3727759868440637]}},{"type":"Feature","properties":{"LAMPPOST_N":"73/1/73/1A"},"geometry":{"type":"Point","coordinates":[103.90870064614931,1.3724823268188882]}},{"type":"Feature","properties":{"LAMPPOST_N":"71/1/71/1A"},"geometry":{"type":"Point","coordinates":[103.90860210912106,1.3721313871253797]}},{"type":"Feature","properties":{"LAMPPOST_N":"69/4/69/1A"},"geometry":{"type":"Point","coordinates":[103.90849234348201,1.3718019876200696]}},{"type":"Feature","properties":{"LAMPPOST_N":"51/4/51/4A"},"geometry":{"type":"Point","coordinates":[103.90744300443113,1.368589663828992]}},{"type":"Feature","properties":{"LAMPPOST_N":"51/3/51/3A"},"geometry":{"type":"Point","coordinates":[103.90736819913818,1.3683737209979205]}},{"type":"Feature","properties":{"LAMPPOST_N":"50S2"},"geometry":{"type":"Point","coordinates":[103.90679544064086,1.365714802906358]}},{"type":"Feature","properties":{"LAMPPOST_N":"50S3"},"geometry":{"type":"Point","coordinates":[103.90671439720897,1.3654865475309914]}},{"type":"Feature","properties":{"LAMPPOST_N":"115S3"},"geometry":{"type":"Point","coordinates":[103.91463622089842,1.379707359264957]}},{"type":"Feature","properties":{"LAMPPOST_N":"112/1/112/1A"},"geometry":{"type":"Point","coordinates":[103.9139216113082,1.378845437082654]}},{"type":"Feature","properties":{"LAMPPOST_N":"91"},"geometry":{"type":"Point","coordinates":[103.91015876463365,1.376332491810748]}},{"type":"Feature","properties":{"LAMPPOST_N":"93"},"geometry":{"type":"Point","coordinates":[103.91045174864755,1.376692588289233]}},{"type":"Feature","properties":{"LAMPPOST_N":"95"},"geometry":{"type":"Point","coordinates":[103.91082106959034,1.3770599506034156]}},{"type":"Feature","properties":{"LAMPPOST_N":"97"},"geometry":{"type":"Point","coordinates":[103.91120641512963,1.3773842067428415]}},{"type":"Feature","properties":{"LAMPPOST_N":"99"},"geometry":{"type":"Point","coordinates":[103.9116324786367,1.3776668006168373]}},{"type":"Feature","properties":{"LAMPPOST_N":"101"},"geometry":{"type":"Point","coordinates":[103.91212263760208,1.3779711110175985]}},{"type":"Feature","properties":{"LAMPPOST_N":"103"},"geometry":{"type":"Point","coordinates":[103.91249436758342,1.3782009598890628]}},{"type":"Feature","properties":{"LAMPPOST_N":"105"},"geometry":{"type":"Point","coordinates":[103.91288276945521,1.3784403178097109]}}]}